<!-- XML代码自动补全 -->
<!-- XML支持 -->
<!-- XML XMLTools -->
<!-- 代码补全 -->
<!-- XML Complete -->
<emps>
    <emp>
        <name>Johon</name>
        <age>33</age>
        <image>https://web-framework.oss-cn-hangzhou.aliyuncs.com/web/1.jpg</image>
        <!-- 1: 男 2：女 -->
        <gender>1</gender>
        <!-- 1：产品 2：项目经理 3：UI -->
        <job>1</job>
    </emp>

    <emp>
        <name>helper</name>
        <age>23</age>
        <image>https://web-framework.oss-cn-hangzhou.aliyuncs.com/web/2.jpg</image>
        <!-- 1: 男 2：女 -->
        <gender>1</gender>
        <!-- 1：产品 2：项目经理 3：UI -->
        <job>1</job>
    </emp>

    <emp>
        <name>roga</name>
        <age>24</age>
        <image>https://web-framework.oss-cn-hangzhou.aliyuncs.com/web/3.jpg</image>
        <!-- 1: 男 2：女 -->
        <gender>2</gender>
        <!-- 1：产品 2：项目经理 3：UI -->
        <job>3</job>
    </emp>

    <emp>
        <name>Josh</name>
        <age>332</age>
        <image>https://web-framework.oss-cn-hangzhou.aliyuncs.com/web/4.jpg</image>
        <!-- 1: 男 2：女 -->
        <gender>1</gender>
        <!-- 1：产品 2：项目经理 3：UI -->
        <job>3</job>
    </emp>
</emps>